dstbn_prob/Binomialdistribution.py
dstbn_prob/Gaussiandistribution.py
dstbn_prob/Generaldistribution.py
dstbn_prob/__init__.py
dstbn_prob-0.1.dist-info/METADATA
dstbn_prob-0.1.dist-info/WHEEL
dstbn_prob-0.1.dist-info/top_level.txt
dstbn_prob-0.1.dist-info/RECORD
