Metadata-Version: 2.1
Name: dstbn_prob
Version: 0.1
Summary: Gaussian distributions
